oppm/__init__.py
oppm/cli.py
oppm/commands.py
oppm/config.py
oppm/exceptions.py
oppm/metadata.py
oppm/shims.py
oppm-0.1.1.dist-info/WHEEL
oppm-0.1.1.dist-info/entry_points.txt
oppm-0.1.1.dist-info/METADATA
oppm-0.1.1.dist-info/RECORD
