Metadata-Version: 2.3
Name: oppm
Version: 0.1.1
Summary: A simple Portable Package Manager written in Python
Requires-Dist: tomlkit>=0.13.3
Requires-Python: >=3.13
